tsfeast/__init__.py
tsfeast/_base.py
tsfeast/funcs.py
tsfeast/metrics.py
tsfeast/models.py
tsfeast/splitter.py
tsfeast/transformers.py
tsfeast/tsfeatures.py
tsfeast/utils.py
tsfeast-0.1.1.dist-info/LICENSE.txt
tsfeast-0.1.1.dist-info/METADATA
tsfeast-0.1.1.dist-info/WHEEL
tsfeast-0.1.1.dist-info/top_level.txt
tsfeast-0.1.1.dist-info/RECORD
